{
  "name": "30 seconds of Python",
  "dirName": "30python",
  "repoUrl": "https://github.com/30-seconds/30-seconds-of-python",
  "snippetPath": "snippets",
  "language": {
    "short": "py",
    "long": "Python"
  },
  "slug": "python",
  "featured": true,
  "biasPenaltyMultiplier": 1,
  "splash": "terrarium.png",
  "description": "The Python snippet collection contains helper functions for Python 3.6. It includes utilities for most common data types, such as primitivies, lists, dictionaries and date objects.",
  "shortDescription": "Browse helper functions for Python 3.6, including utilities for primitives, lists, dictionaries and date objects.",
  "tagMetadata": {
    "math": {
      "splash": "plant-window.png"
    },
    "list": {
      "splash": "widescreen.png"
    },
    "dictionary": {
      "splash": "tea-pour.png"
    }
  }
}
